orange3_nlp-0.0.8.dist-info/licenses/LICENSE
orangecontrib/__init__.py
orangecontrib/nlp/__init__.py
orangecontrib/nlp/util/__init__.py
orangecontrib/nlp/util/apikeys.py
orangecontrib/nlp/util/embedder_models.py
orangecontrib/nlp/util/sentence_truncate.py
orangecontrib/nlp/util/spacy_downloader.py
orangecontrib/nlp/util/udpipe_downloader.py
orangecontrib/nlp/widgets/__init__.py
orangecontrib/nlp/widgets/owabstractive_summary.py
orangecontrib/nlp/widgets/owanaliza_sentymentu.py
orangecontrib/nlp/widgets/owextractive_summary.py
orangecontrib/nlp/widgets/owmodel_doc2vec.py
orangecontrib/nlp/widgets/owmodel_e5.py
orangecontrib/nlp/widgets/owmodel_fasttext.py
orangecontrib/nlp/widgets/owmodel_gemini.py
orangecontrib/nlp/widgets/owmodel_nomic.py
orangecontrib/nlp/widgets/owmodel_openai.py
orangecontrib/nlp/widgets/owmodel_sbert.py
orangecontrib/nlp/widgets/owmodel_spacy.py
orangecontrib/nlp/widgets/owmodel_use.py
orangecontrib/nlp/widgets/owner.py
orangecontrib/nlp/widgets/owollama_rag.py
orangecontrib/nlp/widgets/owpos_tagger.py
orangecontrib/nlp/widgets/owpos_viewer.py
orangecontrib/nlp/widgets/owquestion_answer.py
orangecontrib/nlp/widgets/owreference_library.py
orangecontrib/nlp/widgets/owtext_chunker.py
orangecontrib/nlp/widgets/owtext_embedder.py
orangecontrib/nlp/widgets/owtoken_corpus.py
orangecontrib/nlp/widgets/owtrain_doc2vec.py
orangecontrib/nlp/widgets/icons/nlp-USE.svg
orangecontrib/nlp/widgets/icons/nlp-abstract.svg
orangecontrib/nlp/widgets/icons/nlp-analiza-sentymentu.svg
orangecontrib/nlp/widgets/icons/nlp-chunk.svg
orangecontrib/nlp/widgets/icons/nlp-doc2vec-train.svg
orangecontrib/nlp/widgets/icons/nlp-doc2vec.svg
orangecontrib/nlp/widgets/icons/nlp-e5.svg
orangecontrib/nlp/widgets/icons/nlp-embed.svg
orangecontrib/nlp/widgets/icons/nlp-extract.svg
orangecontrib/nlp/widgets/icons/nlp-fasttext.svg
orangecontrib/nlp/widgets/icons/nlp-gemini.svg
orangecontrib/nlp/widgets/icons/nlp-gensim.svg
orangecontrib/nlp/widgets/icons/nlp-ner.svg
orangecontrib/nlp/widgets/icons/nlp-nomic.svg
orange3_nlp-0.0.8.dist-info/METADATA
orange3_nlp-0.0.8.dist-info/WHEEL
orange3_nlp-0.0.8.dist-info/entry_points.txt
orange3_nlp-0.0.8.dist-info/top_level.txt
orange3_nlp-0.0.8.dist-info/RECORD
