Metadata-Version: 2.4
Name: orange3-nlp
Version: 0.0.8
Summary: A collection of Orange3 widgets to perform natural language processing
Author-email: Chris Lee <github@chrislee.dhs.org>
License: CC-BY-NC-SA-4.0
Project-URL: Homepage, https://github.com/chrislee35/orange3-nlp
Keywords: orange3 add-on
Classifier: Development Status :: 3 - Alpha
Classifier: Intended Audience :: Education
Classifier: Intended Audience :: Science/Research
Classifier: Programming Language :: Python :: 3 :: Only
Requires-Python: >=3.11
License-File: LICENSE
Requires-Dist: Orange3>=3.34.0
Requires-Dist: orange-canvas-core>=0.1.28
Requires-Dist: orange-widget-base>=4.20.0
Requires-Dist: spacy>=3.8.5
Requires-Dist: flair>=0.15.1
Requires-Dist: nltk>=3.9.1
Requires-Dist: numpy==1.26.4
Requires-Dist: sumy>=0.11.0
Requires-Dist: summa>=1.2.0
Requires-Dist: stanza>=1.10.1
Requires-Dist: ufal.udpipe>=1.3.1.1
Requires-Dist: faiss-cpu>=1.11.0
Requires-Dist: sentence_transformers>=4.1.0
Requires-Dist: openai>=1.78.1
Requires-Dist: langchain-text-splitters>=0.3.8
Requires-Dist: gensim>=4.3.3
Requires-Dist: tensorflow>=2.19.0
Requires-Dist: tensorflow-hub>=0.16.1
Requires-Dist: fasttext>=0.9.3
Requires-Dist: google-generativeai>=0.8.5
Requires-Dist: PyQtWebEngine>=5.15.7
Requires-Dist: sacremoses>=0.1.1
Requires-Dist: sentimentpl>=0.0.6
Requires-Dist: semantic-text-splitter>=0.27.0
Provides-Extra: test
Requires-Dist: coverage; extra == "test"
Provides-Extra: doc
Requires-Dist: sphinx; extra == "doc"
Requires-Dist: recommonmark; extra == "doc"
Requires-Dist: sphinx_rtd_theme; extra == "doc"
Dynamic: license-file
